Metadata-Version: 1.0
Name: moby-dict
Version: 0.1.0.post1
Summary: Programmatic access to Moby Project in Python
Home-page: https://github.com/MarcoFavorito/moby_dict
Author: Marco Favorito
Author-email: marco.favorito@gmail.com
License: MIT
Platform: UNKNOWN
